google_photos_library_api/__init__.py
google_photos_library_api/api.py
google_photos_library_api/auth.py
google_photos_library_api/const.py
google_photos_library_api/exceptions.py
google_photos_library_api/model.py
google_photos_library_api/py.typed
google_photos_library_api-1.0.1.dist-info/licenses/LICENSE
google_photos_library_api-1.0.1.dist-info/METADATA
google_photos_library_api-1.0.1.dist-info/WHEEL
google_photos_library_api-1.0.1.dist-info/top_level.txt
google_photos_library_api-1.0.1.dist-info/RECORD
