Metadata-Version: 2.4
Name: google_photos_library_api
Version: 1.0.1
Summary: A python client library for Google Photos Library API
Author-email: Allen Porter <allen.porter@gmail.com>
License-Expression: Apache-2.0
Project-URL: Source, https://github.com/allenporter/python-google-photos-library-api
Requires-Python: >=3.13
License-File: LICENSE
Requires-Dist: aiohttp>=3.7.3
Requires-Dist: mashumaro>=3.12
Dynamic: license-file
